MANIFEST.in
README
requirements.txt
setup.py
ajenti.plugin.cron.egg-info/PKG-INFO
ajenti.plugin.cron.egg-info/SOURCES.txt
ajenti.plugin.cron.egg-info/dependency_links.txt
ajenti.plugin.cron.egg-info/requires.txt
ajenti.plugin.cron.egg-info/top_level.txt
ajenti_plugin_cron/README.md
ajenti_plugin_cron/__init__.py
ajenti_plugin_cron/main.py
ajenti_plugin_cron/manager.py
ajenti_plugin_cron/plugin.yml
ajenti_plugin_cron/requirements.txt
ajenti_plugin_cron/views.py
ajenti_plugin_cron/locale/app.pot
ajenti_plugin_cron/locale/af/LC_MESSAGES/app.js
ajenti_plugin_cron/locale/af/LC_MESSAGES/app.po
ajenti_plugin_cron/locale/ar/LC_MESSAGES/app.js
ajenti_plugin_cron/locale/ar/LC_MESSAGES/app.po
ajenti_plugin_cron/locale/be/LC_MESSAGES/app.js
ajenti_plugin_cron/locale/be/LC_MESSAGES/app.po
ajenti_plugin_cron/locale/bg/LC_MESSAGES/app.js
ajenti_plugin_cron/locale/bg/LC_MESSAGES/app.po
ajenti_plugin_cron/locale/bn/LC_MESSAGES/app.js
ajenti_plugin_cron/locale/bn/LC_MESSAGES/app.po
ajenti_plugin_cron/locale/bs/LC_MESSAGES/app.js
ajenti_plugin_cron/locale/bs/LC_MESSAGES/app.po
ajenti_plugin_cron/locale/ca/LC_MESSAGES/app.js
ajenti_plugin_cron/locale/ca/LC_MESSAGES/app.po
ajenti_plugin_cron/locale/cs/LC_MESSAGES/app.js
ajenti_plugin_cron/locale/cs/LC_MESSAGES/app.po
ajenti_plugin_cron/locale/da/LC_MESSAGES/app.js
ajenti_plugin_cron/locale/da/LC_MESSAGES/app.po
ajenti_plugin_cron/locale/de/LC_MESSAGES/app.js
ajenti_plugin_cron/locale/de/LC_MESSAGES/app.po
ajenti_plugin_cron/locale/el/LC_MESSAGES/app.js
ajenti_plugin_cron/locale/el/LC_MESSAGES/app.po
ajenti_plugin_cron/locale/en/LC_MESSAGES/app.po
ajenti_plugin_cron/locale/eo/LC_MESSAGES/app.js
ajenti_plugin_cron/locale/eo/LC_MESSAGES/app.po
ajenti_plugin_cron/locale/es-ES/LC_MESSAGES/app.js
ajenti_plugin_cron/locale/es-ES/LC_MESSAGES/app.po
ajenti_plugin_cron/locale/et/LC_MESSAGES/app.js
ajenti_plugin_cron/locale/et/LC_MESSAGES/app.po
ajenti_plugin_cron/locale/fa/LC_MESSAGES/app.js
ajenti_plugin_cron/locale/fa/LC_MESSAGES/app.po
ajenti_plugin_cron/locale/fi/LC_MESSAGES/app.js
ajenti_plugin_cron/locale/fi/LC_MESSAGES/app.po
ajenti_plugin_cron/locale/fr/LC_MESSAGES/app.js
ajenti_plugin_cron/locale/fr/LC_MESSAGES/app.po
