Metadata-Version: 1.2
Name: ajenti.plugin.cron
Version: 0.5
Summary: Cron
Home-page: https://ajenti.org
Author: Arnaud Kientz
Author-email: arnaud@linuxmuster.net
License: UNKNOWN
Platform: UNKNOWN
Requires-Python: >=3
